<?xml version="1.0" encoding="UTF-8"?>
<sv:node sv:name="projectSection" xmlns:sv="http://www.jcp.org/jcr/sv/1.0" xmlns:xsi="http://www.w3.org/2001/XMLSchema-instance">
  <sv:property sv:name="jcr:primaryType" sv:type="Name">
    <sv:value>mgnl:contentNode</sv:value>
  </sv:property>
  <sv:property sv:name="jcr:mixinTypes" sv:type="Name" sv:multiple="true">
    <sv:value>mix:lockable</sv:value>
  </sv:property>
  <sv:property sv:name="jcr:uuid" sv:type="String">
    <sv:value>b25f5595-f5ea-40d4-a42d-6c497b3bd712</sv:value>
  </sv:property>
  <sv:property sv:name="id" sv:type="String">
    <sv:value>standard-templating-kit:pages/syntax-gis/projectSection</sv:value>
  </sv:property>
  <sv:property sv:name="jcr:createdBy" sv:type="String">
    <sv:value>admin</sv:value>
  </sv:property>
  <sv:property sv:name="mgnl:activationStatus" sv:type="Boolean">
    <sv:value>false</sv:value>
  </sv:property>
  <sv:property sv:name="mgnl:created" sv:type="Date">
    <sv:value>2014-10-16T11:32:05.153Z</sv:value>
  </sv:property>
  <sv:property sv:name="mgnl:createdBy" sv:type="String">
    <sv:value>superuser</sv:value>
  </sv:property>
  <sv:property sv:name="mgnl:lastActivated" sv:type="Date">
    <sv:value>2014-10-16T11:32:05.155Z</sv:value>
  </sv:property>
  <sv:property sv:name="mgnl:lastActivatedBy" sv:type="String">
    <sv:value>superuser</sv:value>
  </sv:property>
  <sv:property sv:name="mgnl:lastModified" sv:type="Date">
    <sv:value>2014-10-16T14:33:58.951Z</sv:value>
  </sv:property>
  <sv:property sv:name="mgnl:lastModifiedBy" sv:type="String">
    <sv:value>superuser</sv:value>
  </sv:property>
</sv:node>
